amzsc/__init__.py
amzsc/interface.py
amzsc/handlers/__init__.py
amzsc/handlers/error_handler.py
amzsc/models/description.py
amzsc/modules/__init__.py
amzsc/modules/chrome_driver/__init__.py
amzsc/modules/chrome_driver/driver_amazon.py
amzsc/modules/chrome_driver/driver_config.py
amzsc/modules/chrome_driver/driver_manipulator.py
amzsc/modules/proxy/__init__.py
amzsc/modules/proxy/proxy.py
amzsc/modules/proxy/proxy_request.py
amzsc/utils/__init__.py
amzsc/utils/common_paths.py
amzsc/utils/constants.py
amzsc/utils/custom_types.py
amzsc/utils/file_worker.py
amzsc/utils/marketplace.py
amazon_description_scraper-0.1.0.dist-info/METADATA
amazon_description_scraper-0.1.0.dist-info/WHEEL
amazon_description_scraper-0.1.0.dist-info/top_level.txt
amazon_description_scraper-0.1.0.dist-info/RECORD
