Metadata-Version: 2.4
Name: amazon-description-scraper
Version: 0.1.0
Summary: Webscrape project to get Amazon products' descriptions
Author-email: Ryzan Bui <ryzan.b@zendom.co.uk>
Project-URL: Source, https://github.com/ryzanbui02/amazon-description-scraper
Keywords: amazon,scraping
Requires-Python: >=3.9
Requires-Dist: bs4
Requires-Dist: fake-useragent
Requires-Dist: pandas
Requires-Dist: requests
Requires-Dist: selenium
Provides-Extra: test
Requires-Dist: pytest; extra == "test"
Requires-Dist: pytest-cov; extra == "test"
